topdogalerts/__init__.py
topdogalerts/db/__init__.py
topdogalerts/db/connection.py
topdogalerts/evaluation/__init__.py
topdogalerts/evaluation/evaluator.py
topdogalerts/evaluation/expression_ast.py
topdogalerts/evaluation/expression_evaluator.py
topdogalerts/evaluation/expression_parser.py
topdogalerts/evaluation/semantic_evaluator.py
topdogalerts/listener/__init__.py
topdogalerts/listener/base.py
topdogalerts/listener/buffering.py
topdogalerts/listener/logging.py
topdogalerts/listener/notifications.py
topdogalerts/listener/registry.py
topdogalerts/managers/__init__.py
topdogalerts/managers/event_trigger.py
topdogalerts/managers/event_type.py
topdogalerts/models/__init__.py
topdogalerts/models/event_trigger.py
topdogalerts/models/event_type.py
topdogalerts/publisher/__init__.py
topdogalerts/publisher/sqs.py
topdogalerts-2.0.0.dist-info/licenses/LICENSE
topdogalerts-2.0.0.dist-info/METADATA
topdogalerts-2.0.0.dist-info/WHEEL
topdogalerts-2.0.0.dist-info/top_level.txt
topdogalerts-2.0.0.dist-info/RECORD
