Metadata-Version: 2.4
Name: topdogalerts
Version: 2.0.0
Summary: Shared runtime utilities for Top Dog Alerts listeners (DB triggers + SQS events)
Author: Top Dog
Requires-Python: >=3.10
License-File: LICENSE
Requires-Dist: psycopg2-binary>=2.9.0
Requires-Dist: boto3>=1.34.0
Provides-Extra: test
Requires-Dist: pytest>=7.0; extra == "test"
Requires-Dist: pytest-asyncio>=0.21; extra == "test"
Requires-Dist: pytest-cov>=4.0; extra == "test"
Requires-Dist: moto[sqs]>=4.0; extra == "test"
Dynamic: license-file
